tablex/__init__.py
tablex/_constants.py
tablex/_utils.py
tablex/extract.py
tablex/tweet.py
tablex/upload_data.py
tablex_nuuuwan-1.0.3.dist-info/LICENSE
tablex_nuuuwan-1.0.3.dist-info/METADATA
tablex_nuuuwan-1.0.3.dist-info/WHEEL
tablex_nuuuwan-1.0.3.dist-info/top_level.txt
tablex_nuuuwan-1.0.3.dist-info/RECORD
